watson_poetry/plugin.py
watson_poetry-0.2.0.dist-info/METADATA
watson_poetry-0.2.0.dist-info/WHEEL
watson_poetry-0.2.0.dist-info/entry_points.txt
watson_poetry-0.2.0.dist-info/RECORD
