Metadata-Version: 2.1
Name: watson-poetry
Version: 0.2.0
Summary: Build via maturin when changes are detected
Author: Jocelyn-Gas
Author-email: jocelyn.gas@dillygence.com
Requires-Python: >=3.11,<4.0
Classifier: Programming Language :: Python :: 3
Classifier: Programming Language :: Python :: 3.11
Classifier: Programming Language :: Python :: 3.12
Requires-Dist: poetry (>=1.8.2,<2.0.0)
